{
  "https://gov.uniswap.org": 58401,
  "https://forum.makerdao.com": 106395,
  "https://governance.aave.com": 64021,
  "https://www.comp.xyz": 19269,
  "https://forum.arbitrum.foundation": 76661,
  "https://gov.optimism.io": 46383,
  "https://discuss.ens.domains": 61405,
  "https://research.lido.fi": 25383,
  "https://gov.gitcoin.co": 56633,
  "https://forum.safe.global": 13791,
  "https://forum.balancer.fi": 16929,
  "https://dydx.forum": 10765,
  "https://gov.1inch.io": 4326,
  "https://gov.yearn.fi": 36017,
  "https://forum.morpho.org": 3997,
  "https://gov.frax.finance": 8039,
  "https://forum.euler.finance": 4322,
  "https://gov.gmx.io": 12533,
  "https://forum.celo.org": 27802,
  "https://forum.moonwell.fi": 4855,
  "https://forum.zknation.io": 2462,
  "https://forum.berachain.com": 2853,
  "https://discuss.jup.ag": 76852,
  "https://forum.stakewise.io": 4033,
  "https://forum.nexusmutual.io": 4603,
  "https://gov.ethenafoundation.com": 1103,
  "https://gov.centrifuge.io": 20163,
  "https://forum.eigenlayer.xyz": 144836,
  "https://gov.kamino.finance": 1147,
  "https://community.obol.org": 1655,
  "https://forum.ssv.network": 4840,
  "https://forum.staderlabs.com": 3053,
  "https://gov.renzoprotocol.com": 392,
  "https://forum.babylon.foundation": 1233,
  "https://forum.thegraph.com": 13910,
  "https://forum.decentraland.org": 110290,
  "https://gov.indexcoop.com": 17377,
  "https://community.metamask.io": 89613,
  "https://forum.cosmos.network": 39486,
  "https://forum.osmosis.zone": 9206,
  "https://forum.hop.exchange": 3781,
  "https://forum.mantle.xyz": 19661,
  "https://forum.jito.network": 1773,
  "https://forum.marinade.finance": 4288,
  "https://forum.wormhole.com": 1382,
  "https://forum.cow.fi": 8004,
  "https://forum.pyth.network": 6872,
  "https://community.venus.io": 13065,
  "https://gov.velora.xyz": 6971,
  "https://forum.minswap.org": 11733,
  "https://gov.bancor.network": 16242
}
